main/__init__.py
main/flask_service/__init__.py
main/flask_service/main.py
main/flask_service/entity/__init__.py
main/flask_service/entity/bql.py
main/flask_service/exception/__init__.py
main/flask_service/exception/handler.py
bb_connector-0.0.4.dist-info/LICENSE
bb_connector-0.0.4.dist-info/METADATA
bb_connector-0.0.4.dist-info/WHEEL
bb_connector-0.0.4.dist-info/entry_points.txt
bb_connector-0.0.4.dist-info/top_level.txt
bb_connector-0.0.4.dist-info/RECORD
