Metadata-Version: 2.1
Name: bb-connector
Version: 0.0.4
Summary: This project is a flask-service for calculating Bloomberg query's as a REST service.
Author: Richard Maidorn
Author-email: maidorn@orcacapital.de
Project-URL: Source Code, https://gitlab.com/orca-capital/algo-trading/python/bb-connector
Classifier: Programming Language :: Python :: 3
Classifier: License :: OSI Approved :: MIT License
Classifier: Operating System :: Microsoft :: Windows
Requires-Python: >=3.11
License-File: LICENSE
Requires-Dist: xbbg (==0.7.7)
Requires-Dist: pandas (==2.0.3)
Requires-Dist: flask (==2.3.2)
Requires-Dist: pywin32 (==306)
Requires-Dist: waitress (==2.1.2)
Requires-Dist: python-dotenv (==1.0.0)
